{
  "metadata": {
    "lastUpdated": "2025-09-22T10:12:20.939Z",
    "version": "1.0"
  },
  "donations": [
    {
      "id": "DON_2025092201",
      "type": "monetary",
      "details": {
        "donorName": "John Doe",
        "amount": 1000,
        "currency": "INR",
        "purpose": "Flood Relief",
        "paymentMethod": "direct"
      },
      "tracking": {
        "status": "completed",
        "createdBy": "admin",
        "createdAt": "2025-09-22T10:00:00Z",
        "verificationId": "d123"
      },
      "blockchain": {
        "txHash": "0x123",
        "txId": "d123",
        "network": "mumbai",
        "status": "confirmed"
      }
    },
    {
      "id": "DON_2025092202",
      "type": "monetary",
      "details": {
        "donorName": "Jane Smith",
        "amount": 2500,
        "currency": "INR",
        "purpose": "Medical Supplies",
        "paymentMethod": "online"
      },
      "tracking": {
        "status": "completed",
        "createdBy": "admin",
        "createdAt": "2025-09-22T09:23:23.476Z",
        "verificationId": "0x79b91a7820a58ac199e4d07d3063381da5b9df7e6d1b806ffd65270050bb58c9"
      },
      "blockchain": {
        "txHash": "0x456",
        "txId": "0x79b91a7820a58ac199e4d07d3063381da5b9df7e6d1b806ffd65270050bb58c9",
        "network": "mumbai",
        "status": "confirmed"
      }
    },
    {
      "id": "DON_2025092203",
      "type": "monetary",
      "details": {
        "donorName": "Acme Corporation",
        "amount": 50000,
        "currency": "INR",
        "purpose": "Emergency Relief Fund",
        "paymentMethod": "bank_transfer"
      },
      "tracking": {
        "status": "completed",
        "createdBy": "admin",
        "createdAt": "2025-09-22T08:45:00Z",
        "verificationId": "0xabc123"
      },
      "blockchain": {
        "txHash": "0x789",
        "txId": "0xabc123",
        "network": "mumbai",
        "status": "confirmed"
      }
    },
    {
      "id": "DON_2025092204",
      "type": "monetary",
      "details": {
        "donorName": "Anonymous Donor",
        "amount": 15000,
        "currency": "INR",
        "purpose": "Food Distribution",
        "paymentMethod": "direct"
      },
      "tracking": {
        "status": "completed",
        "createdBy": "admin",
        "createdAt": "2025-09-22T07:30:00Z",
        "verificationId": "0xdef456"
      },
      "blockchain": {
        "txHash": "0x101112",
        "txId": "0xdef456",
        "network": "mumbai",
        "status": "confirmed"
      }
    },
    {
      "id": "DON_2025092205",
      "type": "monetary",
      "details": {
        "donorName": "Rajesh Kumar",
        "amount": 5000,
        "currency": "INR",
        "purpose": "Shelter Support",
        "paymentMethod": "online"
      },
      "tracking": {
        "status": "pending",
        "createdBy": "admin",
        "createdAt": "2025-09-22T10:12:20.934Z",
        "verificationId": "0x991524d6ac9609851904eb4335d183a9c5c571007b819b699ccf393b2b55ba64"
      },
      "blockchain": null
    }
  ],
  "supplies": [
    {
      "id": "SUP_2025092201",
      "type": "food",
      "details": {
        "item": "Food Supplies",
        "quantity": 100,
        "unit": "packages",
        "category": "essential"
      },
      "logistics": {
        "from": {
          "name": "Delhi Warehouse",
          "type": "warehouse"
        },
        "to": {
          "name": "Mumbai Relief Center",
          "type": "relief_center"
        },
        "location": {
          "lat": 19.076,
          "lng": 72.8777,
          "locationName": "Mumbai"
        }
      },
      "tracking": {
        "status": "in_transit",
        "trackingId": "s456",
        "createdBy": "admin",
        "createdAt": "2025-09-22T11:00:00Z"
      },
      "blockchain": {
        "txHash": "0x456",
        "trackingId": "s456",
        "network": "mumbai",
        "status": "confirmed"
      }
    },
    {
      "id": "SUP_2025092202",
      "type": "medical",
      "details": {
        "item": "Medical Kits",
        "quantity": 50,
        "unit": "kits",
        "category": "essential"
      },
      "logistics": {
        "from": {
          "name": "Pune Distribution Center",
          "type": "warehouse"
        },
        "to": {
          "name": "Kerala Relief Camp",
          "type": "relief_center"
        },
        "location": {
          "lat": 10.8505,
          "lng": 76.2711,
          "locationName": "Kerala"
        }
      },
      "tracking": {
        "status": "delivered",
        "trackingId": "s789",
        "createdBy": "admin",
        "createdAt": "2025-09-22T09:30:00Z"
      },
      "blockchain": {
        "txHash": "0x789",
        "trackingId": "s789",
        "network": "mumbai",
        "status": "confirmed"
      }
    },
    {
      "id": "SUP_2025092203",
      "type": "shelter",
      "details": {
        "item": "Tents and Tarpaulins",
        "quantity": 200,
        "unit": "pieces",
        "category": "essential"
      },
      "logistics": {
        "from": {
          "name": "Bangalore Logistics Hub",
          "type": "warehouse"
        },
        "to": {
          "name": "Chennai Disaster Zone",
          "type": "relief_center"
        },
        "location": {
          "lat": 13.0827,
          "lng": 80.2707,
          "locationName": "Chennai"
        }
      },
      "tracking": {
        "status": "in_transit",
        "trackingId": "s101112",
        "createdBy": "admin",
        "createdAt": "2025-09-22T08:15:00Z"
      },
      "blockchain": {
        "txHash": "0x101112",
        "trackingId": "s101112",
        "network": "mumbai",
        "status": "confirmed"
      }
    }
  ],
  "feedback": [],
  "statistics": {
    "totalDonations": 73000,
    "totalSupplies": 3,
    "lastDonationDate": "2025-09-22T10:12:20.939Z",
    "lastSupplyDate": "2025-09-22T11:00:00Z"
  }
}
